drugrunner/__init__.py
drugrunner-0.0.1.dist-info/METADATA
drugrunner-0.0.1.dist-info/WHEEL
drugrunner-0.0.1.dist-info/top_level.txt
drugrunner-0.0.1.dist-info/RECORD
